validators/__init__.py
validators/accounts_validator.py
validators/api_validator.py
validators/cards_validator.py
validators/common_validator.py
validators/customer_validate.py
validators/validate.py
openturfpython_sdk-0.1.0.dist-info/METADATA
openturfpython_sdk-0.1.0.dist-info/WHEEL
openturfpython_sdk-0.1.0.dist-info/top_level.txt
openturfpython_sdk-0.1.0.dist-info/RECORD
